prp2022/__init__.py
prp2022-1.0.0.dist-info/LICENSE.txt
prp2022-1.0.0.dist-info/METADATA
prp2022-1.0.0.dist-info/WHEEL
prp2022-1.0.0.dist-info/top_level.txt
prp2022-1.0.0.dist-info/RECORD
